khamyo/__init__.py
khamyo/core.py
khamyo/data.json
KhamYo-0.3.0.dist-info/LICENSE
KhamYo-0.3.0.dist-info/METADATA
KhamYo-0.3.0.dist-info/WHEEL
KhamYo-0.3.0.dist-info/top_level.txt
KhamYo-0.3.0.dist-info/RECORD
