Metadata-Version: 2.1
Name: KhamYo
Version: 0.3.0
Summary: Thai abbreviation to full text library
Home-page: https://github.com/wannaphong/KhamYo
Author: Wannaphong Phatthiyaphaibun
Author-email: wannaphong@yahoo.com
License: Apache Software License 2.0
Project-URL: Source Code, https://github.com/wannaphong/KhamYo
Project-URL: Bug Tracker, https://github.com/wannaphong/KhamYo/issues
Keywords: NLP,natural language processing,text analytics,text processing,localization,computational linguistics,ThaiNLP,Thai NLP,Thai language
Classifier: Development Status :: 5 - Production/Stable
Classifier: Programming Language :: Python :: 3
Classifier: Intended Audience :: Developers
Classifier: License :: OSI Approved :: Apache Software License
Classifier: Natural Language :: Thai
Classifier: Topic :: Scientific/Engineering :: Artificial Intelligence
Classifier: Topic :: Text Processing
Classifier: Topic :: Text Processing :: General
Classifier: Topic :: Text Processing :: Linguistic
Requires-Python: >=3.6
License-File: LICENSE
Requires-Dist: pythainlp >=4.0
Requires-Dist: sentence-transformers
Requires-Dist: transformers
Requires-Dist: sentencepiece
